{
  "extends": [
    // "tslint-config-airbnb",
    "tslint:latest",
    "tslint-react",
    "tslint-config-prettier",
    "tslint-immutable"
  ],
  "rulesDirectory": [
    "tslint-plugin-prettier"
  ],
  "rules": {
    "prettier": true,
    "no-implicit-dependencies": false,
    "no-submodule-imports": false,
    "curly": [true, "ignore-same-line"],
    "interface-name": false,
    "object-literal-sort-keys": false,
    "no-unused-expression": [true, "allow-fast-null-checks"],
    "no-var-keyword": true,
    // "no-parameter-reassignment": true,
    "typedef": [true, "call-signature"],
    "readonly-keyword": true,
    "readonly-array": true,
    "no-let": true,
    "no-object-mutation": true,
    // "no-delete": true,
    "no-method-signature": true,
    "no-this": false,
    "no-class": false,
    // "no-mixed-interface": false,
    "no-expression-statement": false,
    "no-if-statement": false
  }
}